{
  "0": "Authentication & Security",
  "1": "Module: page.tsx",
  "2": "Database & Migrations",
  "3": "Module: page.tsx",
  "4": "Module: route.ts",
  "5": "Module: getAnalyticsDashboardAction()",
  "6": "Module: GET()",
  "7": "Authentication & Security",
  "8": "Module: page.tsx",
  "9": "Lead Management",
  "10": "UI Components",
  "11": "Module: route.ts",
  "12": "Module: generateMetadata()",
  "13": "Module: page.tsx",
  "14": "Module: page.tsx",
  "15": "Module: page.tsx",
  "16": "Module: route.ts",
  "17": "Module: route.ts",
  "18": "Lead Management",
  "19": "Module: page.tsx",
  "20": "Rewards Engine",
  "21": "Module: fetchWith206Fix()",
  "22": "Lead Management",
  "23": "Module: Data Safety & Snapshots",
  "24": "Module: middleware.ts",
  "25": "Module: page.tsx",
  "26": "Module: route.ts",
  "27": "Module: route.ts",
  "28": "Module: route.ts",
  "29": "Module: route.ts",
  "30": "Module: page.tsx",
  "31": "Lead Management",
  "32": "Lead Management",
  "33": "Module: handleSaveContact()",
  "34": "Rewards Engine",
  "35": "Module: seed()",
  "36": "Module: IdleTracker()",
  "37": "Lead Management",
  "38": "Module: check-all-icons.mjs",
  "39": "Admin Dashboard",
  "40": "Module: check-icons.mjs",
  "41": "Module: next-env.d.ts",
  "42": "Module: next.config.js",
  "43": "Module: postcss.config.js",
  "44": "Module: tailwind.config.js",
  "45": "Database & Migrations",
  "46": "Module: page.tsx",
  "47": "Module: schemas.ts",
  "48": "UI Components",
  "49": "UI Components",
  "50": "Database & Migrations",
  "51": "Module: Slideshow.tsx",
  "52": "Module: dynamic.ts",
  "53": "Module: tenant.ts"
}