{"nodes":[{"id":"restore_route","label":"route.ts","file_type":"code","source_file":"C:\\source\\repos\\perso\\WASLA\\smofe\\app\\api\\restore\\route.ts","source_location":"L1"},{"id":"restore_route_requireadmin","label":"requireAdmin()","file_type":"code","source_file":"C:\\source\\repos\\perso\\WASLA\\smofe\\app\\api\\restore\\route.ts","source_location":"L10"},{"id":"restore_route_post","label":"POST()","file_type":"code","source_file":"C:\\source\\repos\\perso\\WASLA\\smofe\\app\\api\\restore\\route.ts","source_location":"L26"}],"edges":[{"source":"restore_route","target":"server","relation":"imports_from","confidence":"EXTRACTED","source_file":"C:\\source\\repos\\perso\\WASLA\\smofe\\app\\api\\restore\\route.ts","source_location":"L2","weight":1},{"source":"restore_route","target":"c_source_repos_perso_wasla_smofe_lib_auth_ts","relation":"imports_from","confidence":"EXTRACTED","source_file":"C:\\source\\repos\\perso\\WASLA\\smofe\\app\\api\\restore\\route.ts","source_location":"L3","weight":1},{"source":"restore_route","target":"c_source_repos_perso_wasla_smofe_lib_db_ts","relation":"imports_from","confidence":"EXTRACTED","source_file":"C:\\source\\repos\\perso\\WASLA\\smofe\\app\\api\\restore\\route.ts","source_location":"L4","weight":1},{"source":"restore_route","target":"c_source_repos_perso_wasla_smofe_src_lib_crypto_ts","relation":"imports_from","confidence":"EXTRACTED","source_file":"C:\\source\\repos\\perso\\WASLA\\smofe\\app\\api\\restore\\route.ts","source_location":"L5","weight":1},{"source":"restore_route","target":"path","relation":"imports_from","confidence":"EXTRACTED","source_file":"C:\\source\\repos\\perso\\WASLA\\smofe\\app\\api\\restore\\route.ts","source_location":"L6","weight":1},{"source":"restore_route","target":"fs","relation":"imports_from","confidence":"EXTRACTED","source_file":"C:\\source\\repos\\perso\\WASLA\\smofe\\app\\api\\restore\\route.ts","source_location":"L7","weight":1},{"source":"restore_route","target":"os","relation":"imports_from","confidence":"EXTRACTED","source_file":"C:\\source\\repos\\perso\\WASLA\\smofe\\app\\api\\restore\\route.ts","source_location":"L8","weight":1},{"source":"restore_route","target":"restore_route_requireadmin","relation":"contains","confidence":"EXTRACTED","source_file":"C:\\source\\repos\\perso\\WASLA\\smofe\\app\\api\\restore\\route.ts","source_location":"L10","weight":1},{"source":"restore_route","target":"restore_route_post","relation":"contains","confidence":"EXTRACTED","source_file":"C:\\source\\repos\\perso\\WASLA\\smofe\\app\\api\\restore\\route.ts","source_location":"L26","weight":1},{"source":"restore_route_post","target":"restore_route_requireadmin","relation":"calls","confidence":"EXTRACTED","source_file":"C:\\source\\repos\\perso\\WASLA\\smofe\\app\\api\\restore\\route.ts","source_location":"L27","weight":1}]}